cuda_tools/__init__.py
cuda_tools/context.py
cuda_tools/decorators.py
cuda_tools/utils.py
universal_cuda_tools-0.8.0.dist-info/METADATA
universal_cuda_tools-0.8.0.dist-info/WHEEL
universal_cuda_tools-0.8.0.dist-info/top_level.txt
universal_cuda_tools-0.8.0.dist-info/RECORD
