Metadata-Version: 2.4
Name: universal-cuda-tools
Version: 0.8.0
Summary: Comprehensive device management for PyTorch & TensorFlow & Universal
Author-email: tunahanyrd <tunahanyrd@gmail.com>
License: MIT
Project-URL: Repository, https://github.com/tunahanyrd/universal-cuda-tools
Requires-Python: >=3.7
Requires-Dist: torch>=1.8.0
Requires-Dist: numpy
Requires-Dist: psutil
Provides-Extra: tf
Requires-Dist: tensorflow; extra == "tf"
Provides-Extra: tpu
Requires-Dist: cloud-tpu-client; extra == "tpu"
Provides-Extra: cupy
Requires-Dist: cupy; extra == "cupy"
